quote_generator/__init__.py
quotes_generator-0.2.dist-info/LICENSE
quotes_generator-0.2.dist-info/METADATA
quotes_generator-0.2.dist-info/WHEEL
quotes_generator-0.2.dist-info/top_level.txt
quotes_generator-0.2.dist-info/RECORD
