Metadata-Version: 2.1
Name: quotes-generator
Version: 0.2
Summary: Best Quotes Generator
Home-page: https://github.com/niteshprajapat/Quotes-Generator
Author: Nitesh Prajapat
Author-email: niteshp282000@gmail.com
License: UNKNOWN
Platform: UNKNOWN
Classifier: Programming Language :: Python :: 3
Classifier: License :: OSI Approved :: MIT License
Classifier: Operating System :: OS Independent
Requires-Python: >=3.6
